microEye/__init__.py
microEye/_version.py
microEye/launcher.py
microEye/qt.py
microEye/analysis/__init__.py
microEye/analysis/checklist_dialog.py
microEye/analysis/cmosMaps.py
microEye/analysis/multi_viewer.py
microEye/analysis/filters/__init__.py
microEye/analysis/filters/base.py
microEye/analysis/filters/spatial.py
microEye/analysis/filters/temporal.py
microEye/analysis/fitting/__init__.py
microEye/analysis/fitting/fit.py
microEye/analysis/fitting/nena.py
microEye/analysis/fitting/phasor_fit.py
microEye/analysis/fitting/processing.py
microEye/analysis/fitting/rcc.py
microEye/analysis/fitting/results.py
microEye/analysis/fitting/results_stats.py
microEye/analysis/fitting/tardis.py
microEye/analysis/fitting/psf/__init__.py
microEye/analysis/fitting/psf/extract.py
microEye/analysis/fitting/psf/rubost_mean.py
microEye/analysis/fitting/psf/spline.py
microEye/analysis/fitting/psf/temp.py
microEye/analysis/fitting/psf/test.py
microEye/analysis/fitting/psf/stats/__init__.py
microEye/analysis/fitting/psf/stats/core.py
microEye/analysis/fitting/psf/stats/curve_fit.py
microEye/analysis/fitting/psf/stats/io.py
microEye/analysis/fitting/psf/stats/slope_fit.py
microEye/analysis/fitting/pyfit3Dcspline/__init__.py
microEye/analysis/fitting/pyfit3Dcspline/constants.py
microEye/analysis/fitting/pyfit3Dcspline/mainfunctions.py
microEye/analysis/fitting/pyfit3Dcspline/CPU/CPUfunctions.py
microEye/analysis/fitting/pyfit3Dcspline/CPU/CPUmleFit_LM.py
microEye/analysis/fitting/pyfit3Dcspline/CPU/CPUsplineLib.py
microEye/analysis/fitting/pyfit3Dcspline/CPU/__init__.py
microEye/analysis/fitting/pyfit3Dcspline/GPU/GPUfunctions.py
microEye/analysis/fitting/pyfit3Dcspline/GPU/GPUmleFit_LM_EMCCD.py
microEye/analysis/fitting/pyfit3Dcspline/GPU/GPUmleFit_LM_sCMOS.py
microEye/analysis/fitting/pyfit3Dcspline/GPU/GPUsplineLib.py
microEye/analysis/fitting/pyfit3Dcspline/GPU/__init__.py
microEye/analysis/processing/__init__.py
microEye/analysis/processing/frc.py
microeye-2.3.12.dist-info/licenses/LICENSE
microeye-2.3.12.dist-info/METADATA
microeye-2.3.12.dist-info/WHEEL
microeye-2.3.12.dist-info/entry_points.txt
microeye-2.3.12.dist-info/top_level.txt
microeye-2.3.12.dist-info/RECORD
