Metadata-Version: 2.4
Name: microeye
Version: 2.3.12
Summary: A python toolkit for fluorescence microscopy         that features hardware control, data analysis and vizualization         for super-resolution single-molecule localization microscopy and         single-partical tracking.
Home-page: https://github.com/samhitech/microEye
Author: Mohammad Nour Alsamsam
Author-email: nour.alsamsam@gmail.com
Project-URL: miEye Paper, https://doi.org/10.1016/j.ohx.2022.e00368
Project-URL: miEye OSF, http://doi.org/10.17605/osf.io/j2fqy
Classifier: Programming Language :: Python :: 3.9
Classifier: Programming Language :: Python :: 3.10
Classifier: Programming Language :: Python :: 3.11
Classifier: License :: OSI Approved :: GNU General Public License v3 (GPLv3)
Classifier: Operating System :: OS Independent
Requires-Python: >=3.9.4, <3.12
License-File: LICENSE
Requires-Dist: autopep8==2.2.0
Requires-Dist: dask==2024.5.2
Requires-Dist: h5py==3.11.0
Requires-Dist: hidapi==0.14.0
Requires-Dist: matplotlib==3.9.2
Requires-Dist: mmpycorex==0.3.16
Requires-Dist: numba==0.60.0
Requires-Dist: numpy==1.26.4
Requires-Dist: ome_types==0.5.2
Requires-Dist: opencv_python==4.9.0.80
Requires-Dist: pandas==2.2.3
Requires-Dist: pco==2.3.0
Requires-Dist: pycromanager==1.0.2
Requires-Dist: pyfiglet==1.0.2
Requires-Dist: pyflakes==3.2.0
Requires-Dist: pyjokes==0.6.0
Requires-Dist: PyOpenGL==3.1.7
Requires-Dist: pypylon==4.2.0
Requires-Dist: pyqtdarktheme==2.1.0
Requires-Dist: pyqtgraph==0.13.7
Requires-Dist: pyserial==3.5
Requires-Dist: PySide6==6.7.2
Requires-Dist: PySide6_Addons==6.7.2
Requires-Dist: PySide6_Essentials==6.7.2
Requires-Dist: pyueye==4.96.952
Requires-Dist: QDarkStyle==3.2.3
Requires-Dist: QScintilla==2.14.1
Requires-Dist: scikit-image==0.22.0
Requires-Dist: scikit_learn==1.5.0
Requires-Dist: scipy==1.14.1
Requires-Dist: setuptools==69.0.2
Requires-Dist: tables==3.9.1
Requires-Dist: tabulate==0.9.0
Requires-Dist: tqdm==4.66.4
Requires-Dist: tifffile==2024.8.10
Requires-Dist: zarr>=2.18.2
Dynamic: author
Dynamic: author-email
Dynamic: classifier
Dynamic: description
Dynamic: description-content-type
Dynamic: home-page
Dynamic: license-file
Dynamic: project-url
Dynamic: requires-dist
Dynamic: requires-python
Dynamic: summary
